{
  "providers": [
    {
      "id": "1",
      "name": "Brian Wood",
      "email": "brianwood@hotmail.com",
      "area": "Nord",
      "job": 1,
      "tel": "06 00 00 00 00",
      "img": "https://picsum.photos/200/300?random=1",
      "des": "description 1"
    },
    {
      "id": "2",
      "name": "Rick",
      "email": "rick@rick.com",
      "area": "Sud",
      "job": 1,
      "tel": "06 00 00 00 00",
      "img": "https://picsum.photos/200/300?random=2",
      "des": "description 2"
    },
    {
      "id": "3",
      "name": "Morthy",
      "email": "test@test.com",
      "area": "Est",
      "job": 3,
      "tel": "06 00 00 00 00",
      "img": "https://picsum.photos/200/300?random=3",
      "des": "description 3"
    },
    {
      "id": "2",
      "name": "Sam",
      "email": "sam@test.com",
      "area": "Ouest",
      "job": 7,
      "tel": "06 00 00 00 00",
      "img": "https://picsum.photos/200/300?random=4",
      "des": "description 4"
    }
  ],
  "jobs": [
    {
      "id": "1",
      "name": "Developer"
    },
    {
      "id": "2",
      "name": "Designer"
    },
    {
      "id": "3",
      "name": "Manager"
    },
    {
      "id": "4",
      "name": "Engineer"
    },
    {
      "id": "5",
      "name": "Analyst"
    },
    {
      "id": "6",
      "name": "Consultant"
    },
    {
      "id": "7",
      "name": "Architect"
    }
  ],
  "users": [
    {
      "id": "1",
      "name": "Brian Wood",
      "email": "brianwood@hotmail.com",
      "area": "Nord",
      "job": 1,
      "tel": "06 00 00 00 00",
      "img": "https://picsum.photos/200/300?random=1",
      "des": "description 1",
      "enabled": false
    },
    {
      "id": "2",
      "name": "Rick",
      "email": "rick@rick.com",
      "area": "Sud",
      "job": 1,
      "tel": "06 00 00 00 00",
      "img": "https://picsum.photos/200/300?random=2",
      "des": "description 2",
      "enabled": false
    },
    {
      "id": "3",
      "name": "Morthy",
      "email": "test@test.com",
      "area": "Est",
      "job": 3,
      "tel": "06 00 00 00 00",
      "img": "https://picsum.photos/200/300?random=3",
      "des": "description 3",
      "enabled": false
    },
    {
      "id": "4",
      "name": "Sam",
      "email": "sam@test.com",
      "area": "Ouest",
      "job": 7,
      "tel": "06 00 00 00 00",
      "img": "https://picsum.photos/200/300?random=4",
      "des": "description 4",
      "enabled": false
    }
  ]
}